raytracemrt/calc_mrt.py
raytracemrt/gen_grids.py
raytracemrt/merge_vox.py
raytracemrt/project.py
raytracemrt/project2box.py
raytracemrt/raytracemrt.py
raytracemrt/utils.py
raytracemrt-0.0.3.dist-info/LICENSE
raytracemrt-0.0.3.dist-info/METADATA
raytracemrt-0.0.3.dist-info/WHEEL
raytracemrt-0.0.3.dist-info/entry_points.txt
raytracemrt-0.0.3.dist-info/top_level.txt
raytracemrt-0.0.3.dist-info/RECORD
