Metadata-Version: 2.1
Name: raytracemrt
Version: 0.0.3
Summary: Python library for calculating MRT Map from Chaosense Sensor
Author-email: Kian Wee CHEN <chenkianwee@gmail.com>
Project-URL: Homepage, https://github.com/chenkianwee/raytracemrt/
Project-URL: Bug Tracker, https://github.com/chenkianwee/raytracemrt/issues
Classifier: License :: OSI Approved :: GNU General Public License v3 (GPLv3)
Classifier: Programming Language :: Python :: 3.11
Classifier: Operating System :: OS Independent
Requires-Python: ==3.11
License-File: LICENSE
Requires-Dist: geomie3d (==0.0.2)
